[{"date":"2018-10-15T12:11:09.845-07:00"},{"author":"321Gold","url":"http://www.321gold.com","css":"head title","new":null},{"author":"321Gold","url":"321gold.com","css":"h3 b","new":0},{"author":"AntiWar","url":"https://www.news.antiwar.com","css":"h1.entry-title","new":null},{"author":"AntiWar","url":"http://www.antiwar.com","css":"header.entry-header h1.entry-title","new":null},{"author":"Antonius Aquinas","url":"https://antoniusaquinas.com","css":"h1.entry-title","new":null},{"author":"Automatic Earth","url":"http://www.theautomaticearth.com","css":"div.title h1.posttitle a","new":null},{"author":"Banyan Hill","url":"banyanhill.com","css":"article h1.entry-title","new":0},{"author":"Birch Gold","url":"https://www.birchgold.com","css":"div.post-title-holder h1.entry-title","new":null},{"author":"Bloomberg","url":"http://www.bloomberg.com","css":"h1[class$=hed]","new":null},{"author":"BullionStar","url":"http://www.bullionstar.com","css":"header.entry-header h1.entry-title","new":null},{"author":"Business Insider","url":"http://www.businessinsider.com.au","css":"div.container h1","new":null},{"author":"CATO Institute","url":"http://www.cato.org","css":"h1#page-title","new":null},{"author":"CNBC","url":"http://www.cnbc.com","css":"h1.title","new":null},{"author":"CNBC","url":"www.cnbc.com","css":".story-top h1.title","new":0},{"author":"Capitalist Exploits","url":"http://www.capitalistexploits.at","css":"h1.entry-title","new":null},{"author":"Casey Research","url":"https://www.caseyresearch.com","css":"h1.entry-header","new":null},{"author":"Clean Technica","url":"http://www.cleantechnica.com","css":"article h1.omc-post-heading-standard","new":null},{"author":"Coin Telegraph","url":"http://www.cointelegraph.com","css":"h1.header","new":null},{"author":"Credit Bubble Bulletin","url":"creditbubblebulletin.com","css":"div.post h3.post-title","new":0},{"author":"Credit Bubble Bulletin","url":"https://www.creditbubblebulletin.blogspot.com","css":"h3.entry-title","new":null},{"author":"Daily Bell","url":"www.thedailybell.com","css":"div.top-article-title","new":0},{"author":"Daily Reckoning","url":"dailyreckoning.com","css":"[class$=article] h1","new":0},{"author":"Daily Reckoning","url":"http://www.dailyreckoning.com","css":"#single-article-body h1","new":null},{"author":"Dana Lyons","url":"http://www.jlfmi.tumblr.com","css":"div.post-bd h2 a","new":null},{"author":"DealBreaker","url":"dealbreaker.com","css":"header h1.post-title","new":0},{"author":"Decentralize Today","url":"http://www.decentralize.today","css":"h1 graf--title","new":null},{"author":"Dr. Sircus","url":"http://www.drsircus.com","css":"h1.entry-title","new":null},{"author":"Engadget","url":"http://www.engadget.com","css":"header h1","new":null},{"author":"Evonomics","url":"http://www.evonomics.com","css":"header.entry-header h1.page-title","new":null},{"author":"Express","url":"www.express.co.uk","css":"article header h1","new":0},{"author":"Felder Report","url":"thefelderreport.com","css":"h1.entry-title","new":0},{"author":"Financial Times","url":"http://www.ft.com","css":"header.trial-subs__heading span.trial-subs__heading-article-title","new":null},{"author":"FiveThirtyEight","url":"https://www.fivethirtyeight.com","css":"h1.article-title","new":null},{"author":"Foreign Policy","url":"http://www.europeslamsitsgates.foreignpolicy.com","css":"div#header1 h1.post-hed","new":null},{"author":"Fortune","url":"https://www.fortune.com","css":"div.article-info h1.headline","new":null},{"author":"Fox \u0026 Hounds","url":"https://www.foxandhoundsdaily.com","css":"h1.entry-heading a","new":null},{"author":"Futurism","url":"http://www.futurism.com","css":"section h1","new":null},{"author":"GATA","url":"https://www.gata.com","css":"h1.title","new":null},{"author":"GoldCore","url":"http://www.goldcore.com","css":"h3.entry-title","new":null},{"author":"GoldMoney","url":"http://www.goldmoney.com","css":"h1","new":null},{"author":"GoldSilver","url":"goldsilver.com","css":"#content-title h1","new":0},{"author":"Greentech Media","url":"www.greentechmedia.com","css":"div.article-header h1.article-page-heading","new":0},{"author":"Greentech Media","url":"www.greentechmedia.com","css":".article-header h1.article-page-heading","new":0},{"author":"Hacker Noon","url":"http://www.hackernoon.com","css":".section-inner h1.graf--title","new":null},{"author":"Independent","url":"http://www.independent.co.uk","css":"article.article-article h1","new":null},{"author":"James Howard Kunstler","url":"https://www.kunstler.com","css":"h1.title","new":null},{"author":"Kitco","url":"http://www.kitco.com","css":"#article-info-title h1","new":null},{"author":"Kunstler","url":"kunstler.com","css":".post h1.title a","new":0},{"author":"Longreads","url":"https://www.longreads.com","css":"h1.entry-title a","new":null},{"author":"Madison","url":"https://www.madison.com","css":"h1.headline span","new":null},{"author":"Manila Bulletin","url":"http://www.business.mb.com.ph","css":"div h1.uk-article-title","new":null},{"author":"MarketWatch","url":"https://www.marketwatch.com","css":".article-headline-wrapper h1","new":null},{"author":"Medium","url":"http://www.medium.com","css":".section-inner h1.graf--title","new":null},{"author":"Mish","url":"www.themaven.net","css":".story-header h1","new":0},{"author":"MunKnee","url":"https://www.munknee.com","css":"h1.entry-title span","new":null},{"author":"NY Times","url":"http://www.nytimes.com","css":"div#story-meta h1#headline","new":null},{"author":"Naked Capitalism","url":"www.nakedcapitalism.com","css":"h2.site-description","new":0},{"author":"Nation","url":"https://www.thenation.com","css":"div.article-header-content h1.title","new":null},{"author":"National Review","url":"www.nationalreview.com","css":"h1.article-header__title","new":0},{"author":"Nestmann","url":"www.nestmann.com","css":"#blog h1","new":0},{"author":"New Yorker","url":"https://www.newyorker.com","css":"header[class^=ArticleHeader] h1","new":null},{"author":"Newsweek","url":"http://www.newsweek.com","css":"header.article-header h1","new":null},{"author":"NorthmanTrader","url":"http://www.northmantrader.com","css":"h1[class*=title]","new":null},{"author":"Oil Price","url":"http://www.oilprice.com","css":"div[class*=Article__wrapper] h1","new":null},{"author":"Peak Prosperity","url":"www.peakprosperity.com","css":".article-details h1.title","new":0},{"author":"Peak Prosperity","url":"https://www.peakprosperity.com","css":"div#content-inner-inner h1.title","new":null},{"author":"Phil's Stock World","url":"www.philstockworld.com","css":".post h1 a","new":0},{"author":"Philly Tribune","url":"https://www.phillytrib.com","css":"header.asset-header h1 span","new":null},{"author":"PressTV","url":"www.presstv.com","css":"article h2.page-header","new":0},{"author":"RT","url":"https://www.rt.com","css":"h1.article__heading","new":null},{"author":"Real Investment Advice","url":"http://www.realinvestmentadvice.com","css":".cont-text h1 a","new":null},{"author":"Renegade Inc.","url":"https://www.renegadeinc.com","css":"h1.entry-title","new":null},{"author":"Reuters","url":"http://www.reuters.com","css":"h1[class^=ArticleHeader_headline]","new":null},{"author":"Right Scoop","url":"http://www.therightscoop.com","css":"header.entry-header h1.entry-title","new":null},{"author":"SRSrocco Report","url":"srsroccoreport.com","css":"article h1.entry-header","new":0},{"author":"Schiff Gold","url":"http://www.schiffgold.com","css":"div.wpb_wrapper h1#welcome-header","new":null},{"author":"Silicon","url":"http://www.silicon.co.uk","css":"header.entry-header .entry-title","new":null},{"author":"Slate","url":"http://www.slate.com","css":"h1.hed","new":null},{"author":"Straight Line Logic","url":"https://www.straightlinelogic.com","css":"h1.entry-title","new":null},{"author":"Telegraph","url":"http://www.telegraph.co.uk","css":"div.component-content h1.headline_-heading","new":null},{"author":"The Street","url":"http://www.thestreet.com","css":"h1.article__headline","new":null},{"author":"Vanity Fair","url":"www.vanityfair.com","css":"article h1.hed","new":0},{"author":"WaPo","url":"https://www.washingtonpost.com","css":"manual","new":null},{"author":"Weekly Times Now","url":"https://www.weeklytimesnow.com.au","css":"manual","new":null},{"author":"Wired","url":"http://www.wired.com","css":"h1.title","new":null},{"author":"Yahoo!","url":"http://www.yahoo.com","css":"header.canvas-header h1","new":null},{"author":"Yahoo!","url":"https://www.finance.yahoo.com","css":"header.canvas-header h1","new":null},{"author":"Zero Hedge","url":"http://www.zerohedge.com","css":".article-list .title","new":null},{"author":"manual","url":"https://hackernoon.com/the-five-keys-to-crypto-evolution-94be921e6354","css":"manual","new":1},{"author":"manual","url":"https://www.thetechnicaltraders.com/partners/idevaffiliate.php?id=115\u0026url=http://www.thetechnicaltraders.com/part-v-chinaasia-economic-implosion-on-the-horizon/","css":"manual","new":1},{"author":"manual","url":"http://www.scmp.com/news/china/economy/article/2140243/chinas-biggest-region-halts-all-government-projects-crackdown","css":"manual","new":1},{"author":"manual","url":"https://www.zerohedge.com/news/2018-04-04/boj-goes-record-etf-buying-spree-prevent-market-rout","css":"manual","new":1},{"author":"manual","url":"https://www.refinery29.com/2018/04/195260/new-york-cuomo-abuse-gun-law","css":"manual","new":1},{"author":"manual","url":"https://www.philstockworld.com/2018/04/04/retaliation-wednesday-the-empire-strikes-back/","css":"manual","new":1},{"author":"manual","url":"http://www.chicagotribune.com/news/opinion/editorials/ct-edit-chicago-pensions-rahm-emanuel-20180403-story.html","css":"manual","new":1},{"author":"manual","url":"https://medium.com/newsvoice/chris-hedges-u-s-citizens-are-living-in-an-inverted-totalitarian-country-c973b3908b70","css":"manual","new":1},{"author":"manual","url":"https://www.zerohedge.com/news/2018-04-07/retail-real-estate-bubble-turns-manhattan-shopping-wasteland","css":"manual","new":1},{"author":"manual","url":"http://www.gata.org/node/18159","css":"manual","new":1},{"author":"manual","url":"http://news.goldseek.com/GoldSeek/1523190360.php","css":"manual","new":1},{"author":"manual","url":"http://aheadoftheherd.com/Newsletter/2018/Gold-Holding-Its-Own.pdf","css":"manual","new":1},{"author":"manual","url":"https://www.nytimes.com/2018/04/06/business/us-china-trade-endgame.html","css":"manual","new":1},{"author":"manual","url":"https://www.reuters.com/article/us-usa-trade-autos/trump-administration-mulls-stiffer-rules-for-imported-cars-idUSKCN1HD2M8","css":"manual","new":1},{"author":"manual","url":"https://www.zerohedge.com/news/2018-04-06/private-equity-firm-offers-cash-strapped-connecticut-2bn-government-buildings","css":"manual","new":1},{"author":"manual","url":"https://medium.com/@caityjohnstone/new-syrian-chemical-weapons-attack-being-reported-by-all-the-usual-suspects-bb52e9a4f982","css":"manual","new":1},{"author":"manual","url":"https://www.zerohedge.com/news/2018-04-10/tuesday-humor-facebook-employees-speak-out","css":"manual","new":1},{"author":"manual","url":"http://theenergycollective.com/roger-arnold/2430631/a-new-look-at-the-hydrogen-economy","css":"manual","new":1},{"author":"manual","url":"http://newseminency.com/2018/04/09/global-solid-oxide-fuel-cell-sofc-market-2018-2023/","css":"manual","new":1},{"author":"manual","url":"http://www.goldtelegraph.com/central-bank-effect-wall-street","css":"manual","new":1},{"author":"manual","url":"http://www.t.co","css":"manual","new":null},{"author":"manual","url":"https://www.caseyresearch.com/americas-two-party-system-is-done/","css":"manual","new":1},{"author":"manual","url":"https://bankingjournal.aba.com/2018/04/artificial-intelligence-the-next-frontier-of-cyber-warfare/","css":"manual","new":1},{"author":"manual","url":"https://projectchesapeake.wordpress.com/2018/03/19/surviving-the-next-great-depression/","css":"manual","new":1},{"author":"manual","url":"https://www.cnbc.com/2018/04/07/japan-activates-first-marines-since-ww2-to-bolster-defenses-against-china.html","css":"manual","new":1},{"author":"manual","url":"https://extranewsfeed.com/former-presidents-meet-secretly-to-discuss-taking-action-against-trump-3afc74ee4417","css":"manual","new":1},{"author":"manual","url":"https://srsroccoreport.com/two-mines-supply-half-of-u-s-silver-production-the-real-cost-to-produce-silver/","css":"manual","new":1},{"author":"manual","url":"https://www.fool.com/investing/2018/04/03/better-stock-yamana-gold-auy-vs-goldcorp-gg.aspx","css":"manual","new":1},{"author":"manual","url":"https://www.marketwatch.com/story/eurozone-inflation-rises-after-months-of-declines-2018-04-04","css":"manual","new":1},{"author":"manual","url":"https://medium.com/@jimmysong/why-bitcoin-is-different-e17b813fd947","css":"manual","new":1},{"author":"manual","url":"https://www.reuters.com/article/us-china-cenbank/global-central-banks-can-adopt-negative-rates-as-conventional-tool-pboc-working-paper-idUSKCN1HA0Q9","css":"manual","new":1},{"author":"manual","url":"https://www.project-syndicate.org/commentary/trump-currency-war-with-china-by-benjamin-j--cohen-2018-04","css":"manual","new":1},{"author":"manual","url":"http://news.goldseek.com/GoldSeek/1522872000.php","css":"manual","new":1},{"author":"manual","url":"https://www.nytimes.com/2018/04/03/us/politics/trump-border-immigration-caravan.html","css":"manual","new":1},{"author":"manual","url":"https://investorplace.com/2018/04/its-time-to-short-tesla-inc-stock/","css":"manual","new":1},{"author":"manual","url":"https://www.marketwatch.com/story/teslas-battered-bonds-rally-after-company-says-it-doesnt-need-to-raise-more-money-this-year-2018-04-04","css":"manual","new":1},{"author":"manual","url":"https://techcrunch.com/2018/04/03/wheres-the-beef-for-impossible-foods-its-in-boosting-burger-sales-and-raising-hundreds-of-millions/amp/","css":"manual","new":1},{"author":"manual","url":"https://www.cnbc.com/2018/04/04/how-to-delete-everything-facebook-knows-about-you.html","css":"manual","new":1},{"author":"manual","url":"https://medium.com/@caityjohnstone/everything-keeps-changing-about-the-skripal-narrative-except-russia-definitely-did-it-80589c52b8df","css":"manual","new":1},{"author":"manual","url":"https://www.cnbc.com/2018/04/04/facebook-updates-the-number-of-users-impacted-by-cambridge-analytica-leak-to-87-million-.html","css":"manual","new":1},{"author":"manual","url":"https://www.nytimes.com/2018/04/04/climate/animals-seasons-mismatch.html","css":"manual","new":1},{"author":"manual","url":"https://aeon.co/essays/how-lyme-disease-became-the-first-epidemic-of-climate-change","css":"manual","new":1},{"author":"manual","url":"https://www.cnbc.com/id/105113671","css":"manual","new":1},{"author":"manual","url":"https://www.barrons.com/articles/netflix-why-its-virtually-impossible-to-call-it-a-buy-1522853233","css":"manual","new":1}]